.testr.conf
AUTHORS
COPYING.txt
ChangeLog
INSTALL.txt
MANIFEST.in
Makefile
NEWS
README.txt
requirements.txt
setup.cfg
setup.py
test-requirements.txt
doc/DESIGN.txt
doc/DEVELOPMENT.txt
doc/MANUAL.txt
l_mirror/__init__.py
l_mirror/gpg.py
l_mirror/journals.py
l_mirror/logging_support.py
l_mirror/main.py
l_mirror/mirrorset.py
l_mirror/server.py
l_mirror/arguments/__init__.py
l_mirror/arguments/command.py
l_mirror/arguments/path.py
l_mirror/arguments/string.py
l_mirror/arguments/url.py
l_mirror/commands/__init__.py
l_mirror/commands/commands.py
l_mirror/commands/finish_change.py
l_mirror/commands/help.py
l_mirror/commands/init.py
l_mirror/commands/mirror.py
l_mirror/commands/serve.py
l_mirror/commands/start_change.py
l_mirror/tests/__init__.py
l_mirror/tests/logging_resource.py
l_mirror/tests/matchers.py
l_mirror/tests/memory_transport_stat.py
l_mirror/tests/monkeypatch.py
l_mirror/tests/stubhome.py
l_mirror/tests/stubpackage.py
l_mirror/tests/test_arguments.py
l_mirror/tests/test_commands.py
l_mirror/tests/test_journals.py
l_mirror/tests/test_logging_resource.py
l_mirror/tests/test_logging_support.py
l_mirror/tests/test_matchers.py
l_mirror/tests/test_mirrorset.py
l_mirror/tests/test_monkeypatch.py
l_mirror/tests/test_server.py
l_mirror/tests/test_setup.py
l_mirror/tests/test_stubhome.py
l_mirror/tests/test_stubpackage.py
l_mirror/tests/test_ui.py
l_mirror/tests/arguments/__init__.py
l_mirror/tests/arguments/test_command.py
l_mirror/tests/arguments/test_path.py
l_mirror/tests/arguments/test_string.py
l_mirror/tests/arguments/test_url.py
l_mirror/tests/commands/__init__.py
l_mirror/tests/commands/test_commands.py
l_mirror/tests/commands/test_finish_change.py
l_mirror/tests/commands/test_help.py
l_mirror/tests/commands/test_init.py
l_mirror/tests/commands/test_mirror.py
l_mirror/tests/commands/test_serve.py
l_mirror/tests/commands/test_start_change.py
l_mirror/tests/ui/__init__.py
l_mirror/tests/ui/test_cli.py
l_mirror/ui/__init__.py
l_mirror/ui/cli.py
lmirror.egg-info/PKG-INFO
lmirror.egg-info/SOURCES.txt
lmirror.egg-info/dependency_links.txt
lmirror.egg-info/entry_points.txt
lmirror.egg-info/not-zip-safe
lmirror.egg-info/requires.txt
lmirror.egg-info/top_level.txt