Metadata-Version: 1.1
Name: lmirror
Version: 0.0.3
Summary: Large scale mirror protocol.
Home-page: https://launchpad.net/lmirror
Author: Robert Collins
Author-email: robertc@robertcollins.net
License: UNKNOWN
Platform: UNKNOWN
Classifier: Intended Audience :: System Administrators
Classifier: Operating System :: POSIX :: Linux
Classifier: Programming Language :: Python
Classifier: Programming Language :: Python :: 2
Classifier: Programming Language :: Python :: 2.7
